{
  "available_on_brokers": true,
  "category": "Sports",
  "collateral_return_type": "MECNET",
  "event_ticker": "KXLOLGAME-26JAN23DNSCGENGA",
  "mutually_exclusive": true,
  "product_metadata": {
    "competition": "League of Legends",
    "competition_scope": "Game"
  },
  "series_ticker": "KXLOLGAME",
  "strike_period": "",
  "sub_title": "DN SOOPers Challengers vs. Gen.G Global Academy (Jan 23)",
  "title": "LCK Challengers League Kickoff 2026: DN SOOPers Challengers vs. Gen.G Global Academy"
}